[{
	"native": "Angst ",
	"foreign": "fear"
}, {
	"native": "Ansatz ",
	"foreign": "entry"
}, {
	"native": "Anschluss ",
	"foreign": "connection"
}, {
	"native": "Automat ",
	"foreign": "machine"
}, {
	"native": "Fest",
	"foreign": "party"
}, {
	"native": "Kraut",
	"foreign": "herb"
}, {
	"native": "Rucksack",
	"foreign": "backpack"
}, {
	"native": "Nudel ",
	"foreign": "pasta"
}, {
	"native": "Auch",
	"foreign": "too"
}, {
	"native": "Woche",
	"foreign": "week"
}, {
	"native": "Auto",
	"foreign": "car"
}, {
	"native": "Flughafen",
	"foreign": "Airport"
}, {
	"native": "Leben",
	"foreign": "life"
}, {
	"native": "Schicksal",
	"foreign": "Destiny"
}, {
	"native": "Hafen",
	"foreign": "port"
}, {
	"native": "Ehrlich",
	"foreign": "Honest"
}, {
	"native": "Rechner",
	"foreign": "computer"
}, {
	"native": "Flugzeug",
	"foreign": "plane"
}, {
	"native": "Schrank",
	"foreign": "closet"
}, {
	"native": "Weg",
	"foreign": "path"
}, {
	"native": "Freiheit",
	"foreign": "freedom"
}]